reahl/domainuiegg.py
reahl/domainui/__init__.py
reahl/domainui/bootstrap/__init__.py
reahl/domainui/bootstrap/accounts.py
reahl/domainui/bootstrap/workflow.py
reahl/domainui_dev/__init__.py
reahl/domainui_dev/fixtures.py
reahl/domainui_dev/bootstrap/__init__.py
reahl/domainui_dev/bootstrap/test_account.py
reahl/domainui_dev/bootstrap/test_workflow.py
reahl/messages/reahl-domainui
reahl/messages/af/LC_MESSAGES/reahl-domainui.mo
reahl/messages/af/LC_MESSAGES/reahl-domainui.po
reahl_domainui-7.0.3.dist-info/LICENSE
reahl_domainui-7.0.3.dist-info/METADATA
reahl_domainui-7.0.3.dist-info/WHEEL
reahl_domainui-7.0.3.dist-info/entry_points.txt
reahl_domainui-7.0.3.dist-info/reahl-component.toml
reahl_domainui-7.0.3.dist-info/top_level.txt
reahl_domainui-7.0.3.dist-info/RECORD
